LICENSE
README.rst
setup.py
bin/sbotmp
sbo_templates/__init__.py
sbo_templates/__metadata__.py
sbo_templates/main.py
sbo_templates/templates.py
sbo_templates.egg-info/PKG-INFO
sbo_templates.egg-info/SOURCES.txt
sbo_templates.egg-info/dependency_links.txt
sbo_templates.egg-info/requires.txt
sbo_templates.egg-info/top_level.txt