Metadata-Version: 2.1
Name: sbo-templates
Version: 1.3.3
Summary: SBo tool for managing templates.
Home-page: https://gitlab.com/dslackw/sbo-templates
Author: dslackw
Author-email: d.zlatanidis@gmail.com
License: UNKNOWN
Keywords: sbo,templates,slackbuild
Platform: UNKNOWN
Classifier: Development Status :: 5 - Production/Stable
Classifier: License :: OSI Approved :: GNU General Public License v3 or later (GPLv3+)
Classifier: Operating System :: Unix
Classifier: Programming Language :: Python
Classifier: Programming Language :: Python :: 3
Requires-Python: >=3.7
License-File: LICENSE
